test/__init__.py
test/test_utils.py
test/test_blocks/__init__.py
test/test_blocks/test_ScalingBlock.py
test/test_layers/__init__.py
test/test_layers/test_channel_attention.py
test/test_layers/test_spatial_attention.py
test/test_layers/test_squeeze_and_excitation.py
useful_layers/__init__.py
useful_layers/utils.py
useful_layers/blocks/ABCBlock.py
useful_layers/blocks/__init__.py
useful_layers/blocks/scaling_block.py
useful_layers/layers/ABCLayer.py
useful_layers/layers/__init__.py
useful_layers/layers/channel_attention.py
useful_layers/layers/spatial_attention.py
useful_layers/layers/squeeze_and_excitation.py
useful_layers-0.0a0.dev2.dist-info/LICENSE
useful_layers-0.0a0.dev2.dist-info/METADATA
useful_layers-0.0a0.dev2.dist-info/WHEEL
useful_layers-0.0a0.dev2.dist-info/top_level.txt
useful_layers-0.0a0.dev2.dist-info/RECORD
