Metadata-Version: 2.1
Name: useful-layers
Version: 0.0a0.dev2
Summary: Useful Layers is a torch based library containing some experimental, but useful layers 
Home-page: https://jernsting.github.io/useful_layers/
Author: Jan Ernsting
Author-email: j.ernsting@uni-muenster.de
License: UNKNOWN
Download-URL: https://github.com/jernsting/useful_layers/archive/0.0a0.dev2.tar.gz
Project-URL: Source Code, https://github.com/jernsting/useful_layers
Project-URL: Documentation, https://jernsting.github.io/useful_layers/
Project-URL: Bug Tracker, https://github.com/jernsting/useful_layers/issues
Keywords: machine learning,deep learning,experimental,science
Platform: UNKNOWN
Classifier: Development Status :: 2 - Pre-Alpha
Classifier: Intended Audience :: Developers
Classifier: Intended Audience :: Science/Research
Classifier: License :: OSI Approved :: MIT License
Classifier: Programming Language :: Python :: 3
Classifier: Topic :: Scientific/Engineering :: Artificial Intelligence
License-File: LICENSE
